{"code":200,"data":[{"devid":3265,"devname":"zigbee\u7f51\u5173\u6a21\u5757","sn":"Tu8tu_Gateway_0001","gid":6375,"uid":7629153,"status":1,"online":0,"hide":1},{"devid":3264,"devname":"\u571f\u5df4\u5154\u667a\u6167\u5bb6\u5206\u5e03\u5f0f\u9762\u677f","sn":"Tu8tu_Router_0003","gid":6375,"uid":7629153,"status":1,"online":0,"hide":1},{"devid":3263,"devname":"\u571f\u5df4\u5154MCU802","sn":"Tu8tu_MCU_0003","gid":6375,"uid":7629153,"status":1,"online":0,"hide":1},{"devid":3262,"devname":"zigbee\u7f51\u5173\u6a21\u5757","sn":"Tu8tu_Gateway_0001","gid":6380,"uid":7967721,"status":1,"online":0,"hide":1},{"devid":3261,"devname":"\u571f\u5df4\u5154\u667a\u6167\u5bb6\u5206\u5e03\u5f0f\u9762\u677f","sn":"Tu8tu_Router_0003","gid":6431,"uid":8691194,"status":1,"online":0,"hide":1},{"devid":3260,"devname":"\u571f\u5df4\u5154MCU802","sn":"Tu8tu_MCU_0003","gid":6431,"uid":8691194,"status":1,"online":0,"hide":1},{"devid":3259,"devname":"\u706f9","sn":"lumi.ctrl_ln2.aq1","gid":6356,"uid":8723911,"status":1,"online":1,"hide":0},{"devid":3258,"devname":"\u706f9","sn":"lumi.ctrl_ln2.aq1","gid":6356,"uid":8723911,"status":1,"online":1,"hide":0},{"devid":3257,"devname":"\u706f","sn":"lumi.ctrl_ln2.aq1","gid":6356,"uid":0,"status":1,"online":0,"hide":0},{"devid":3256,"devname":"\u571f\u5df4\u5154\u667a\u6167\u5bb6\u5343\u5146\u7f51\u7edc\u7cfb\u7edf","sn":"Tu8tu_Router_0002","gid":6345,"uid":0,"status":1,"online":0,"hide":1},{"devid":3255,"devname":"\u571f\u5df4\u5154MCU801","sn":"Tu8tu_MCU_0002","gid":6345,"uid":0,"status":1,"online":0,"hide":1},{"devid":3254,"devname":"zigbee\u7f51\u5173\u6a21\u5757","sn":"Tu8tu_Gateway_0001","gid":5520,"uid":8452915,"status":1,"online":0,"hide":1},{"devid":3253,"devname":"\u571f\u5df4\u5154MCU","sn":"Tu8tu_MCU_0001","gid":5520,"uid":8452915,"status":1,"online":0,"hide":1},{"devid":3252,"devname":"\u63d2\u5ea7","sn":"lumi.ctrl_86plug.aq1","gid":6317,"uid":2433528,"status":1,"online":0,"hide":0},{"devid":3251,"devname":"\u63d2\u5ea7","sn":"lumi.ctrl_86plug.aq1","gid":6317,"uid":2433528,"status":1,"online":0,"hide":0},{"devid":3250,"devname":"\u63d2\u5ea7","sn":"lumi.ctrl_86plug.aq1","gid":6317,"uid":2433528,"status":1,"online":0,"hide":0},{"devid":3249,"devname":"\u5c0f\u767d\u673a\u5668\u4eba","sn":"gowild_robot_ap","gid":0,"uid":2433528,"status":1,"online":1,"hide":0},{"devid":3248,"devname":"zigbee\u7f51\u5173\u6a21\u5757","sn":"Tu8tu_Gateway_0001","gid":6307,"uid":8008213,"status":1,"online":0,"hide":1},{"devid":3247,"devname":"\u571f\u5df4\u5154\u667a\u6167\u5bb6\u5206\u5e03\u5f0f\u9762\u677fPLUS","sn":"Tu8tu_Router_0004","gid":6307,"uid":7629153,"status":1,"online":0,"hide":1},{"devid":3246,"devname":"\u571f\u5df4\u5154MCU802PLUS","sn":"Tu8tu_MCU_0004","gid":6307,"uid":7629153,"status":1,"online":0,"hide":1}],"count":2876,"totalPage":144}