{"code":200,"data":[{"devid":1680,"devname":"\u79fb\u52a8\u706f","sn":"lumi.ctrl_ln1","gid":0,"uid":0,"status":-1,"online":0,"hide":0},{"devid":1679,"devname":"\u706fa12","sn":"lumi.ctrl_ln2","gid":6454,"uid":7288144,"status":-1,"online":0,"hide":0},{"devid":1678,"devname":"\u706fa11","sn":"lumi.ctrl_ln2","gid":6454,"uid":7288144,"status":-1,"online":0,"hide":0},{"devid":1677,"devname":"\u706f","sn":"lumi.ctrl_ln2","gid":6454,"uid":0,"status":-1,"online":0,"hide":0},{"devid":1676,"devname":"\u6444\u50cf\u673a","sn":"Ys_camera_C6H","gid":0,"uid":0,"status":-1,"online":1,"hide":0},{"devid":1675,"devname":"\u4eba\u4f53\u79fb\u52a8\u4f20\u611f\u5668","sn":"LH02121","gid":5931,"uid":0,"status":-1,"online":0,"hide":0},{"devid":1674,"devname":"\u71c3\u6c14\u63a2\u6d4b\u5668","sn":"LH04121","gid":5931,"uid":0,"status":-1,"online":0,"hide":0},{"devid":1673,"devname":"\u706f","sn":"lumi.ctrl_ln2","gid":5146,"uid":0,"status":1,"online":0,"hide":0},{"devid":1672,"devname":"\u706f","sn":"lumi.ctrl_ln2","gid":5146,"uid":0,"status":1,"online":0,"hide":0},{"devid":1671,"devname":"\u7a97\u5e18","sn":"lumi.curtain","gid":5146,"uid":0,"status":1,"online":0,"hide":0},{"devid":1670,"devname":"\u70df\u96fe\u63a2\u6d4b\u56682","sn":"LH05121","gid":6454,"uid":0,"status":-1,"online":1,"hide":0},{"devid":1669,"devname":"\u60c5\u666f\u6309\u94ae","sn":"lumi.ctrl_ln1","gid":5655,"uid":8050381,"status":1,"online":0,"hide":0},{"devid":1668,"devname":"1\u706fA4","sn":"lumi.ctrl_ln1","gid":6295,"uid":0,"status":-1,"online":0,"hide":0},{"devid":1667,"devname":"\u6444\u50cf\u673a","sn":"Ys_camera_C6H","gid":0,"uid":8186281,"status":1,"online":1,"hide":0},{"devid":1666,"devname":"\u4eba\u4f53\u79fb\u52a8\u4f20\u611f\u5668","sn":"LH02121","gid":6130,"uid":8186281,"status":1,"online":0,"hide":0},{"devid":1665,"devname":"\u70df\u96fe\u63a2\u6d4b\u5668","sn":"LH05121","gid":6130,"uid":8186281,"status":1,"online":0,"hide":0},{"devid":1664,"devname":"\u6444\u50cf\u673a","sn":"Ys_camera_C6H","gid":0,"uid":0,"status":-1,"online":1,"hide":0},{"devid":1663,"devname":"\u4eba\u4f53\u79fb\u52a8\u4f20\u611f\u5668","sn":"LH02121","gid":6102,"uid":8185770,"status":1,"online":0,"hide":0},{"devid":1662,"devname":"zigbee\u7f51\u5173\u6a21\u5757","sn":"Tu8tu_Gateway_0001","gid":6130,"uid":8186281,"status":1,"online":0,"hide":1},{"devid":1661,"devname":"\u571f\u5df4\u5154MCU","sn":"Tu8tu_MCU_0001","gid":6130,"uid":8186281,"status":1,"online":0,"hide":1}],"count":2876,"totalPage":144}